MANIFEST.in
README.md
setup.py
sticky/__init__.py
sticky/sticky.py
sticky.egg-info/PKG-INFO
sticky.egg-info/SOURCES.txt
sticky.egg-info/dependency_links.txt
sticky.egg-info/top_level.txt