Metadata-Version: 1.0
Name: sticky
Version: 0.3
Summary: Sticky on Terminal
Home-page: https://github.com/keroro520/Sticky
Author: keroro520
Author-email: keroro520@gmail.com
License: MIT License
Platform: linux
